azure_functions_runtime_v1/__init__.py
azure_functions_runtime_v1/functions.py
azure_functions_runtime_v1/handle_event.py
azure_functions_runtime_v1/loader.py
azure_functions_runtime_v1/logging.py
azure_functions_runtime_v1/otel.py
azure_functions_runtime_v1/version.py
azure_functions_runtime_v1/bindings/context.py
azure_functions_runtime_v1/bindings/datumdef.py
azure_functions_runtime_v1/bindings/generic.py
azure_functions_runtime_v1/bindings/meta.py
azure_functions_runtime_v1/bindings/nullable_converters.py
azure_functions_runtime_v1/bindings/out.py
azure_functions_runtime_v1/bindings/retrycontext.py
azure_functions_runtime_v1/bindings/tracecontext.py
azure_functions_runtime_v1/utils/__init__.py
azure_functions_runtime_v1/utils/app_setting_manager.py
azure_functions_runtime_v1/utils/constants.py
azure_functions_runtime_v1/utils/executor.py
azure_functions_runtime_v1/utils/helpers.py
azure_functions_runtime_v1/utils/threadpool.py
azure_functions_runtime_v1/utils/tracing.py
azure_functions_runtime_v1/utils/typing_inspect.py
azure_functions_runtime_v1/utils/validators.py
azure_functions_runtime_v1/utils/wrappers.py
tests/protos/FunctionRpc_pb2.py
tests/protos/FunctionRpc_pb2_grpc.py
tests/protos/__init__.py
tests/protos/identity/ClaimsIdentityRpc_pb2.py
tests/protos/identity/ClaimsIdentityRpc_pb2_grpc.py
tests/protos/identity/__init__.py
tests/protos/shared/NullableTypes_pb2.py
tests/protos/shared/NullableTypes_pb2_grpc.py
tests/protos/shared/__init__.py
tests/unittests/test_app_setting_manager.py
tests/unittests/test_code_quality.py
tests/unittests/test_datumdef.py
tests/unittests/test_handle_event.py
tests/unittests/test_logging.py
tests/unittests/test_nullable_converters.py
tests/unittests/test_opentelemetry.py
tests/unittests/test_rpc_messages.py
tests/unittests/test_threadpool.py
tests/unittests/test_types.py
tests/unittests/test_typing_inspect.py
tests/unittests/test_utilities.py
tests/unittests/default_template/__init__.py
tests/utils/__init__.py
azure_functions_runtime_v1-1.0.0.dist-info/METADATA
azure_functions_runtime_v1-1.0.0.dist-info/WHEEL
azure_functions_runtime_v1-1.0.0.dist-info/top_level.txt
azure_functions_runtime_v1-1.0.0.dist-info/RECORD
