Metadata-Version: 2.4
Name: azure-functions-runtime-v1
Version: 1.0.0
Summary: Python Language Worker for Azure Functions V1 Runtime
Author-email: "Azure Functions team at Microsoft Corp." <azurefunctions@microsoft.com>
Project-URL: Documentation, https://github.com/Azure/azure-functions-python-worker/blob/dev/azure_functions_runtime_v1/README.md
Project-URL: Repository, https://github.com/Azure/azure-functions-python-worker
Keywords: azure,functions,azurefunctions,python,serverless
Classifier: Development Status :: 5 - Production/Stable
Classifier: Programming Language :: Python
Classifier: Programming Language :: Python :: 3
Classifier: Programming Language :: Python :: 3.13
Classifier: Operating System :: Microsoft :: Windows
Classifier: Operating System :: POSIX
Classifier: Operating System :: MacOS :: MacOS X
Classifier: Environment :: Web Environment
Classifier: License :: OSI Approved :: MIT License
Classifier: Intended Audience :: Developers
Requires-Python: >=3.13
Requires-Dist: azure-functions
Provides-Extra: dev
Requires-Dist: azure-monitor-opentelemetry; extra == "dev"
Requires-Dist: flake8==6.*; extra == "dev"
Requires-Dist: pytest; extra == "dev"
Requires-Dist: requests==2.*; extra == "dev"
Requires-Dist: coverage; extra == "dev"
Requires-Dist: grpcio~=1.70.0; extra == "dev"
Requires-Dist: grpcio-tools~=1.70.0; extra == "dev"
Requires-Dist: protobuf~=5.29.0; extra == "dev"
Requires-Dist: pytest-sugar; extra == "dev"
Requires-Dist: pytest-cov; extra == "dev"
Requires-Dist: pytest-xdist; extra == "dev"
Requires-Dist: pytest-randomly; extra == "dev"
Requires-Dist: pytest-instafail; extra == "dev"
Requires-Dist: pytest-rerunfailures; extra == "dev"
Requires-Dist: pytest-asyncio; extra == "dev"
Requires-Dist: pre-commit; extra == "dev"
Requires-Dist: invoke; extra == "dev"
